bookRecommender/VERSION
bookRecommender/__init__.py
bookRecommender/config.yml
bookRecommender/pipeline.py
bookRecommender/predict.py
bookRecommender/train_pipeline.py
bookRecommender/config/__init__.py
bookRecommender/config/core.py
bookRecommender/datasets/BX-Book-Ratings.csv
bookRecommender/datasets/BX-Books.csv
bookRecommender/datasets/BX-Users.csv
bookRecommender/datasets/__init__.py
bookRecommender/processing/__init__.py
bookRecommender/processing/data_manager.py
bookRecommender/processing/features.py
bookRecommender/processing/validation.py
bookRecommender/trained_models/__init__.py
bookRecommender/trained_models/book_recommender_model_output_v0.0.6.pkl
book_recommender-0.0.6.dist-info/METADATA
book_recommender-0.0.6.dist-info/WHEEL
book_recommender-0.0.6.dist-info/top_level.txt
book_recommender-0.0.6.dist-info/RECORD
